coredump_debugger-0.0.4.dist-info/licenses/LICENSE
dpdb/__init__.py
dpdb/__main__.py
dpdb/core_dump.py
dpdb/interface.py
coredump_debugger-0.0.4.dist-info/METADATA
coredump_debugger-0.0.4.dist-info/WHEEL
coredump_debugger-0.0.4.dist-info/entry_points.txt
coredump_debugger-0.0.4.dist-info/top_level.txt
coredump_debugger-0.0.4.dist-info/RECORD
