Metadata-Version: 2.4
Name: coredump-debugger
Version: 0.0.4
Summary: Python core dump system for post-mortem debugging
Author-email: starreeze <starreeze@foxmail.com>
License-Expression: GPL-3.0-or-later
Classifier: Programming Language :: Python :: 3
Classifier: Operating System :: POSIX :: Linux
Classifier: Operating System :: Microsoft :: Windows
Classifier: Operating System :: MacOS
Requires-Python: >=3.8
License-File: LICENSE
Requires-Dist: rich
Provides-Extra: dev
Requires-Dist: term_background; extra == "dev"
Dynamic: license-file
